emanjson2imodxf/__init__.py
emanjson2imodxf/_version.py
emanjson2imodxf/data_munging.py
emanjson2imodxf/emanjson2imodxf.py
emanjson2imodxf-0.0.4.dist-info/LICENSE
emanjson2imodxf-0.0.4.dist-info/METADATA
emanjson2imodxf-0.0.4.dist-info/WHEEL
emanjson2imodxf-0.0.4.dist-info/entry_points.txt
emanjson2imodxf-0.0.4.dist-info/top_level.txt
emanjson2imodxf-0.0.4.dist-info/RECORD
