Metadata-Version: 2.1
Name: emanjson2imodxf
Version: 0.0.4
Summary: Convert tilt-series alignments from EMAN2 to IMOD format.
Home-page: https://github.com/alisterburt/emanjson2imodxf
Author: Alister Burt
Author-email: alisterburt@gmail.com
License: BSD license
Project-URL: Source Code, https://github.com/alisterburt/emanjson2imodxf
Platform: UNKNOWN
Classifier: Development Status :: 2 - Pre-Alpha
Classifier: License :: OSI Approved :: BSD License
Classifier: Natural Language :: English
Classifier: Programming Language :: Python :: 3
Classifier: Programming Language :: Python :: 3.7
Classifier: Programming Language :: Python :: 3.8
Classifier: Programming Language :: Python :: 3.9
Requires-Python: >=3.7
License-File: LICENSE
Requires-Dist: numpy
Requires-Dist: click
Provides-Extra: dev
Requires-Dist: pytest ; extra == 'dev'
Requires-Dist: pre-commit ; extra == 'dev'
